Workbook

Sheet Таамаглал
A1: Таамаглал (шар нүдийг өөрчил) | B1: Утга | C1: Тайлбар / эх сурвалж
A2: Pro сарын үнэ (НӨАТ орсон), ₮ | B2: 9900 | C2: plans хүснэгт
A3: Pro жилийн үнэ, ₮ | B3: 79000 | C3: plans
A4: Pro — жилээр төлөгчийн хувь | B4: 0.5 | C4: зорилт ✱
A5: Team суудал сарын үнэ, ₮ | B5: 5000 | C5: plans
A6: Team суудал жилийн үнэ, ₮ | B6: 50000 | C6: plans
A7: Team — жилээр төлөгчийн хувь | B7: 0.7 | C7: зорилт ✱
A8: НӨАТ (үнэд багтсан) | B8: 0.1 | C8: НӨАТ-ын хууль; 50 сая₮-өөс дээш заавал, сайн дураар 10 сая₮-өөс
A9: QPay шимтгэл (дотоод карт/банк) | B9: 0.01 | C9: TDB merchant нөхцөл ✱ — гэрээгээр батал
A10: ААНОАТ (орлогын ≤300 сая₮ бол 1%) | B10: 0.01 | C10: Конcерватив: цэвэр орлогоос тооцов ✱
A11: Хувьсах зардал / Pro хэрэглэгч / сар (AI, имэйл, storage), ₮ | B11: 500 | C11: ✱
A12: Хувьсах зардал / Team суудал / сар, ₮ | B12: 300 | C12: ✱
A13: Домэйн + Apple/Google (сард хуваасан), ₮ | B13: 50000 | C13: COSTS.md
... A17: Сценарийн коэффициент (0.5 / 1.0 / 1.5) | B17: 1 | C17: Хэрэглэгчийн тоог үржүүлнэ
A19: Pro ARPA (НӨАТ орсон), ₮ | B19: =(1-Таамаглал!$B$4)*Таамаглал!$B$2+Таамаглал!$B$4*Таамаглал!$B$3/12
A20: Team суудлын ARPA, ₮ | B20: =(1-Таамаглал!$B$7)*Таамаглал!$B$5+Таамаглал!$B$7*Таамаглал!$B$6/12
A22: Ханш: 1 USD = 3,595.56₮ (Монголбанк, 2026-09-25). ✱ = таамаг — бодит өгөгдлөөр сар бүр шинэчил.

Sheet 12 сар (P&L)
A1: Мөр / Сар | B1: 1-р сар | C1: 2-р сар | D1: 3-р сар | E1: 4-р сар | F1: 5-р сар | G1: 6-р сар | H1: 7-р сар | I1: 8-р сар | J1: 9-р сар | K1: 10-р сар | L1: 11-р сар | M1: 12-р сар | N1: 12 сар нийт
A2: Төлбөртэй Pro хэрэглэгч (төлөвлөгөө) | B2: 33 | C2: 67 | D2: 100 | E2: 183 | F2: 267 | G2: 350 | H2: 442 | I2: 533 | J2: 625 | K2: 717 | L2: 808 | M2: 900
A3: Team суудал (төлөвлөгөө) | B3: 20 | C3: 40 | D3: 60 | E3: 123 | F3: 187 | G3: 250 | H3: 342 | I3: 433 | J3: 525 | K3: 617 | L3: 708 | M3: 800
A4: Pro × сценари | B4: =B2*Таамаглал!$B$17 | C4: =C2*Таамаглал!$B$17 | D4: =D2*Таамаглал!$B$17 | E4: =E2*Таамаглал!$B$17 | F4: =F2*Таамаглал!$B$17 | G4: =G2*Таамаглал!$B$17 | H4: =H2*Таамаглал!$B$17 | I4: =I2*Таамаглал!$B$17 | ... M4: =M2*Таамаглал!$B$17
A5: Суудал × сценари | B5: =B3*Таамаглал!$B$17 | C5: =C3*Таамаглал!$B$17 | D5: =D3*Таамаглал!$B$17 | E5: =E3*Таамаглал!$B$17 | F5: =F3*Таамаглал!$B$17 | G5: =G3*Таамаглал!$B$17 | H5: =H3*Таамаглал!$B$17 | I5: =I3*Таамаглал!$B$17 | ... M5: =M3*Таамаглал!$B$17
A6: Нийт борлуулалт (НӨАТ орсон) | B6: =B4*Таамаглал!$B$19+B5*Таамаглал!$B$20 | C6: =C4*Таамаглал!$B$19+C5*Таамаглал!$B$20 | D6: =D4*Таамаглал!$B$19+D5*Таамаглал!$B$20 | E6: =E4*Таамаглал!$B$19+E5*Таамаглал!$B$20 | F6: =F4*Таамаглал!$B$19+F5*Таамаглал!$B$20 | G6: =G4*Таамаглал!$B$19+G5*Таамаглал!$B$20 | H6: =H4*Таамаглал!$B$19+H5*Таамаглал!$B$20 | I6: =I4*Таамаглал!$B$19+I5*Таамаглал!$B$20 | ... M6: =M4*Таамаглал!$B$19+M5*Таамаглал!$B$20 | N6: =SUM(B6:M6)
A7: НӨАТ (төсөвт төлнө) | B7: =B6-B8 | C7: =C6-C8 | D7: =D6-D8 | E7: =E6-E8 | F7: =F6-F8 | G7: =G6-G8 | H7: =H6-H8 | I7: =I6-I8 | ... M7: =M6-M8 | N7: =SUM(B7:M7)
A8: Цэвэр орлого | B8: =B6/(1+Таамаглал!$B$8) | C8: =C6/(1+Таамаглал!$B$8) | D8: =D6/(1+Таамаглал!$B$8) | E8: =E6/(1+Таамаглал!$B$8) | F8: =F6/(1+Таамаглал!$B$8) | G8: =G6/(1+Таамаглал!$B$8) | H8: =H6/(1+Таамаглал!$B$8) | I8: =I6/(1+Таамаглал!$B$8) | ... M8: =M6/(1+Таамаглал!$B$8) | N8: =SUM(B8:M8)
A9: QPay шимтгэл | B9: =B6*Таамаглал!$B$9 | C9: =C6*Таамаглал!$B$9 | D9: =D6*Таамаглал!$B$9 | E9: =E6*Таамаглал!$B$9 | F9: =F6*Таамаглал!$B$9 | G9: =G6*Таамаглал!$B$9 | H9: =H6*Таамаглал!$B$9 | I9: =I6*Таамаглал!$B$9 | ... M9: =M6*Таамаглал!$B$9 | N9: =SUM(B9:M9)
A10: Хувьсах зардал (AI, имэйл) | B10: =B4*Таамаглал!$B$11+B5*Таамаглал!$B$12 | C10: =C4*Таамаглал!$B$11+C5*Таамаглал!$B$12 | D10: =D4*Таамаглал!$B$11+D5*Таамаглал!$B$12 | E10: =E4*Таамаглал!$B$11+E5*Таамаглал!$B$12 | F10: =F4*Таамаглал!$B$11+F5*Таамаглал!$B$12 | G10: =G4*Таамаглал!$B$11+G5*Таамаглал!$B$12 | H10: =H4*Таамаглал!$B$11+H5*Таамаглал!$B$12 | I10: =I4*Таамаглал!$B$11+I5*Таамаглал!$B$12 | ... M10: =M4*Таамаглал!$B$11+M5*Таамаглал!$B$12 | N10: =SUM(B10:M10)
A11: Дэд бүтэц (Supabase, Netlify, Resend…) | B11: 200000 | C11: 200000 | D11: 200000 | E11: 400000 | F11: 400000 | G11: 400000 | H11: 400000 | I11: 400000 | J11: 600000 | K11: 600000 | L11: 600000 | M11: 600000 | N11: =SUM(B11:M11)
A12: Нийт ашиг (gross profit) | B12: =B8-B9-B10-B11 | C12: =C8-C9-C10-C11 | D12: =D8-D9-D10-D11 | E12: =E8-E9-E10-E11 | F12: =F8-F9-F10-F11 | G12: =G8-G9-G10-G11 | H12: =H8-H9-H10-H11 | I12: =I8-I9-I10-I11 | ... M12: =M8-M9-M10-M11 | N12: =SUM(B12:M12)
A13: Gross margin % | B13: =IF(B8=0,0,B12/B8) | C13: =IF(C8=0,0,C12/C8) | D13: =IF(D8=0,0,D12/D8) | E13: =IF(E8=0,0,E12/E8) | F13: =IF(F8=0,0,F12/F8) | G13: =IF(G8=0,0,G12/G8) | H13: =IF(H8=0,0,H12/H8) | I13: =IF(I8=0,0,I12/I8) | ... M13: =IF(M8=0,0,M12/M8)
A14: Домэйн + store | B14: =Таамаглал!$B$13 | C14: =Таамаглал!$B$13 | D14: =Таамаглал!$B$13 | E14: =Таамаглал!$B$13 | F14: =Таамаглал!$B$13 | G14: =Таамаглал!$B$13 | H14: =Таамаглал!$B$13 | I14: =Таамаглал!$B$13 | ... M14: =Таамаглал!$B$13 | N14: =SUM(B14:M14)
A15: Нягтлан | B15: =Таамаглал!$B$14 | C15: =Таамаглал!$B$14 | D15: =Таамаглал!$B$14 | E15: =Таамаглал!$B$14 | F15: =Таамаглал!$B$14 | G15: =Таамаглал!$B$14 | H15: =Таамаглал!$B$14 | I15: =Таамаглал!$B$14 | ... M15: =Таамаглал!$B$14 | N15: =SUM(B15:M15)
A16: Маркетинг | B16: =Таамаглал!$B$15 | C16: =Таамаглал!$B$15 | D16: =Таамаглал!$B$15 | E16: =Таамаглал!$B$15 | F16: =Таамаглал!$B$15 | G16: =Таамаглал!$B$15 | H16: =Таамаглал!$B$15 | I16: =Таамаглал!$B$15 | ... M16: =Таамаглал!$B$15 | N16: =SUM(B16:M16)
A17: Цалин | B17: =Таамаглал!$B$16 | C17: =Таамаглал!$B$16 | D17: =Таамаглал!$B$16 | E17: =Таамаглал!$B$16 | F17: =Таамаглал!$B$16 | G17: =Таамаглал!$B$16 | H17: =Таамаглал!$B$16 | I17: =Таамаглал!$B$16 | ... M17: =Таамаглал!$B$16 | N17: =SUM(B17:M17)
A18: Үйл ажиллагааны зардал | B18: =B14+B15+B16+B17 | C18: =C14+C15+C16+C17 | D18: =D14+D15+D16+D17 | E18: =E14+E15+E16+E17 | F18: =F14+F15+F16+F17 | G18: =G14+G15+G16+G17 | H18: =H14+H15+H16+H17 | I18: =I14+I15+I16+I17 | ... M18: =M14+M15+M16+M17 | N18: =SUM(B18:M18)
A19: Татварын өмнөх ашиг | B19: =B12-B18 | C19: =C12-C18 | D19: =D12-D18 | E19: =E12-E18 | F19: =F12-F18 | G19: =G12-G18 | H19: =H12-H18 | I19: =I12-I18 | ... M19: =M12-M18 | N19: =SUM(B19:M19)
A20: ААНОАТ | B20: =B8*Таамаглал!$B$10 | C20: =C8*Таамаглал!$B$10 | D20: =D8*Таамаглал!$B$10 | E20: =E8*Таамаглал!$B$10 | F20: =F8*Таамаглал!$B$10 | G20: =G8*Таамаглал!$B$10 | H20: =H8*Таамаглал!$B$10 | I20: =I8*Таамаглал!$B$10 | ... M20: =M8*Таамаглал!$B$10 | N20: =SUM(B20:M20)
A21: ЦЭВЭР АШИГ | B21: =B19-B20 | C21: =C19-C20 | D21: =D19-D20 | E21: =E19-E20 | F21: =F19-F20 | G21: =G19-G20 | H21: =H19-H20 | I21: =I19-I20 | ... M21: =M19-M20 | N21: =SUM(B21:M21)
A22: Хуримтлагдсан ашиг (мөнгөний хэрэгцээ) | B22: =B21 | C22: =B22+C21 | D22: =C22+D21 | E22: =D22+E21 | F22: =E22+F21 | G22: =F22+G21 | H22: =G22+H21 | I22: =H22+I21 | J22: =I22+J21 | ... M22: =L22+M21 | N22: =MIN(B22:M22) | O22: ← хамгийн бага = шаардлагатай мөнгө

Sheet Сценари
A1: Сценари | B1: Коэф. | C1: 12 сарын борлуулалт (НӨАТ орсон) | D1: 12 сарын цэвэр ашиг | E1: Мөнгөний хэрэгцээ (хамгийн бага хуримтлал) | F1: Анхны ашигтай сар
A2: Болгоомжтой | B2: 0.5 | C2: 29772396 | D2: -9174568 | E2: -12408924 | F2: 9
A3: Суурь | B3: 1 | C3: 59544792 | D3: 15450865 | E3: -7395938 | F3: 6
A4: Өөдрөг | B4: 1.5 | C4: 89317188 | D4: 40076297 | E4: -5349806 | F4: 5
A6: Энэ хуудас нь скриптээр тооцсон тогтмол утга. Өөр утга авах бол «Таамаглал»-ын коэффициентыг өөрчилж «12 сар (P&L)»-г хар.
